aiondata/__init__.py
aiondata/datasets.py
aiondata/processed/bindingaffinity.py
aiondata/raw/bindingdb.py
aiondata/raw/moleculenet.py
aiondata/raw/protein_structure.py
aiondata/raw/uniprot.py
aiondata/raw/weizmann_ccca.py
aiondata/raw/zinc.py
aiondata-0.7.1.dist-info/LICENSE
aiondata-0.7.1.dist-info/METADATA
aiondata-0.7.1.dist-info/WHEEL
aiondata-0.7.1.dist-info/RECORD
