Metadata-Version: 2.1
Name: aiondata
Version: 0.7.1
Summary: A common data access layer for AI-driven drug discovery.
Home-page: https://www.github.com/aion-labs/aiondata
License: Apache
Author: JJ Ben-Joseph
Author-email: jj@tensorspace.ai
Requires-Python: >=3.10,<3.13
Classifier: Development Status :: 3 - Alpha
Classifier: Intended Audience :: Developers
Classifier: Intended Audience :: Science/Research
Classifier: License :: OSI Approved :: Apache Software License
Classifier: License :: Other/Proprietary License
Classifier: Operating System :: OS Independent
Classifier: Programming Language :: Python :: 3
Classifier: Programming Language :: Python :: 3.10
Classifier: Programming Language :: Python :: 3.11
Classifier: Programming Language :: Python :: 3.12
Classifier: Programming Language :: Python :: 3 :: Only
Classifier: Topic :: Scientific/Engineering
Classifier: Topic :: Scientific/Engineering :: Artificial Intelligence
Classifier: Topic :: Scientific/Engineering :: Bio-Informatics
Classifier: Topic :: Scientific/Engineering :: Chemistry
Classifier: Topic :: Scientific/Engineering :: Information Analysis
Classifier: Topic :: Scientific/Engineering :: Medical Science Apps.
Requires-Dist: biopython
Requires-Dist: numpy (>=1.25.2,<2.0.0) ; python_version >= "3.10" and python_version < "4.0"
Requires-Dist: numpy (>=1.25.2,<2.0.0) ; python_version >= "3.11" and python_version < "4.0"
Requires-Dist: numpy (>=1.26.0,<2.0.0) ; python_version >= "3.12" and python_version < "4.0"
Requires-Dist: polars (>=0.20.30) ; python_version >= "3.10"
Requires-Dist: pypdb
Requires-Dist: rdkit
Requires-Dist: scipy
Requires-Dist: tqdm
Requires-Dist: xlsx2csv
